{
  "status": "ok",
  "epoch": 357,
  "epochNonce": "0f4f2d585932024e65f1785462902e2b0508c16c1724e0b8054ea9151065383c",
  "consensus": "tpraos",
  "epochSlots": 28,
  "epochSlotsIdeal": 34.95,
  "maxPerformance": 80.11,
  "poolId": "6c518b4861bb88b1395ceb116342cecbcfb8736282655f9a61c4c368",
  "sigma": 0.001617959181769731,
  "activeStake": 39652009076283,
  "totalActiveStake": 24507422389303696,
  "d": 0,
  "f": 0.05,
  "assignedSlots": [
    {
      "no": 1,
      "slot": 68872597,
      "slotInEpoch": 11797,
      "at": "2022-08-14T03:01:28+02:00"
    },
    {
      "no": 2,
      "slot": 68890941,
      "slotInEpoch": 30141,
      "at": "2022-08-14T08:07:12+02:00"
    },
    {
      "no": 3,
      "slot": 68966879,
      "slotInEpoch": 106079,
      "at": "2022-08-15T05:12:50+02:00"
    },
    {
      "no": 4,
      "slot": 68979042,
      "slotInEpoch": 118242,
      "at": "2022-08-15T08:35:33+02:00"
    },
    {
      "no": 5,
      "slot": 68997819,
      "slotInEpoch": 137019,
      "at": "2022-08-15T13:48:30+02:00"
    },
    {
      "no": 6,
      "slot": 69010188,
      "slotInEpoch": 149388,
      "at": "2022-08-15T17:14:39+02:00"
    },
    {
      "no": 7,
      "slot": 69015130,
      "slotInEpoch": 154330,
      "at": "2022-08-15T18:37:01+02:00"
    },
    {
      "no": 8,
      "slot": 69049362,
      "slotInEpoch": 188562,
      "at": "2022-08-16T04:07:33+02:00"
    },
    {
      "no": 9,
      "slot": 69074839,
      "slotInEpoch": 214039,
      "at": "2022-08-16T11:12:10+02:00"
    },
    {
      "no": 10,
      "slot": 69084380,
      "slotInEpoch": 223580,
      "at": "2022-08-16T13:51:11+02:00"
    },
    {
      "no": 11,
      "slot": 69094033,
      "slotInEpoch": 233233,
      "at": "2022-08-16T16:32:04+02:00"
    },
    {
      "no": 12,
      "slot": 69094354,
      "slotInEpoch": 233554,
      "at": "2022-08-16T16:37:25+02:00"
    },
    {
      "no": 13,
      "slot": 69097053,
      "slotInEpoch": 236253,
      "at": "2022-08-16T17:22:24+02:00"
    },
    {
      "no": 14,
      "slot": 69102069,
      "slotInEpoch": 241269,
      "at": "2022-08-16T18:46:00+02:00"
    },
    {
      "no": 15,
      "slot": 69114501,
      "slotInEpoch": 253701,
      "at": "2022-08-16T22:13:12+02:00"
    },
    {
      "no": 16,
      "slot": 69124940,
      "slotInEpoch": 264140,
      "at": "2022-08-17T01:07:11+02:00"
    },
    {
      "no": 17,
      "slot": 69130034,
      "slotInEpoch": 269234,
      "at": "2022-08-17T02:32:05+02:00"
    },
    {
      "no": 18,
      "slot": 69136798,
      "slotInEpoch": 275998,
      "at": "2022-08-17T04:24:49+02:00"
    },
    {
      "no": 19,
      "slot": 69138105,
      "slotInEpoch": 277305,
      "at": "2022-08-17T04:46:36+02:00"
    },
    {
      "no": 20,
      "slot": 69174283,
      "slotInEpoch": 313483,
      "at": "2022-08-17T14:49:34+02:00"
    },
    {
      "no": 21,
      "slot": 69177348,
      "slotInEpoch": 316548,
      "at": "2022-08-17T15:40:39+02:00"
    },
    {
      "no": 22,
      "slot": 69178567,
      "slotInEpoch": 317767,
      "at": "2022-08-17T16:00:58+02:00"
    },
    {
      "no": 23,
      "slot": 69184690,
      "slotInEpoch": 323890,
      "at": "2022-08-17T17:43:01+02:00"
    },
    {
      "no": 24,
      "slot": 69258002,
      "slotInEpoch": 397202,
      "at": "2022-08-18T14:04:53+02:00"
    },
    {
      "no": 25,
      "slot": 69262839,
      "slotInEpoch": 402039,
      "at": "2022-08-18T15:25:30+02:00"
    },
    {
      "no": 26,
      "slot": 69267936,
      "slotInEpoch": 407136,
      "at": "2022-08-18T16:50:27+02:00"
    },
    {
      "no": 27,
      "slot": 69290064,
      "slotInEpoch": 429264,
      "at": "2022-08-18T22:59:15+02:00"
    },
    {
      "no": 28,
      "slot": 69290797,
      "slotInEpoch": 429997,
      "at": "2022-08-18T23:11:28+02:00"
    }
  ]
}
