{
  "status": "ok",
  "epoch": 374,
  "epochNonce": "53606952e39eadd5eea559be517f9741c9538073e987ec1b7a6c7a05db6195d3",
  "consensus": "praos",
  "epochSlots": 28,
  "epochSlotsIdeal": 28.23,
  "maxPerformance": 99.19,
  "poolId": "6c518b4861bb88b1395ceb116342cecbcfb8736282655f9a61c4c368",
  "sigma": 0.0013069590156341536,
  "activeStake": 32801775588778,
  "totalActiveStake": 25097784395987464,
  "d": 0,
  "f": 0.05,
  "assignedSlots": [
    {
      "no": 1,
      "slot": 76205017,
      "slotInEpoch": 217,
      "at": "2022-11-06T22:48:28+01:00"
    },
    {
      "no": 2,
      "slot": 76219348,
      "slotInEpoch": 14548,
      "at": "2022-11-07T02:47:19+01:00"
    },
    {
      "no": 3,
      "slot": 76230101,
      "slotInEpoch": 25301,
      "at": "2022-11-07T05:46:32+01:00"
    },
    {
      "no": 4,
      "slot": 76278618,
      "slotInEpoch": 73818,
      "at": "2022-11-07T19:15:09+01:00"
    },
    {
      "no": 5,
      "slot": 76284900,
      "slotInEpoch": 80100,
      "at": "2022-11-07T20:59:51+01:00"
    },
    {
      "no": 6,
      "slot": 76299712,
      "slotInEpoch": 94912,
      "at": "2022-11-08T01:06:43+01:00"
    },
    {
      "no": 7,
      "slot": 76306199,
      "slotInEpoch": 101399,
      "at": "2022-11-08T02:54:50+01:00"
    },
    {
      "no": 8,
      "slot": 76311246,
      "slotInEpoch": 106446,
      "at": "2022-11-08T04:18:57+01:00"
    },
    {
      "no": 9,
      "slot": 76335519,
      "slotInEpoch": 130719,
      "at": "2022-11-08T11:03:30+01:00"
    },
    {
      "no": 10,
      "slot": 76336422,
      "slotInEpoch": 131622,
      "at": "2022-11-08T11:18:33+01:00"
    },
    {
      "no": 11,
      "slot": 76358929,
      "slotInEpoch": 154129,
      "at": "2022-11-08T17:33:40+01:00"
    },
    {
      "no": 12,
      "slot": 76360714,
      "slotInEpoch": 155914,
      "at": "2022-11-08T18:03:25+01:00"
    },
    {
      "no": 13,
      "slot": 76367214,
      "slotInEpoch": 162414,
      "at": "2022-11-08T19:51:45+01:00"
    },
    {
      "no": 14,
      "slot": 76384198,
      "slotInEpoch": 179398,
      "at": "2022-11-09T00:34:49+01:00"
    },
    {
      "no": 15,
      "slot": 76399639,
      "slotInEpoch": 194839,
      "at": "2022-11-09T04:52:10+01:00"
    },
    {
      "no": 16,
      "slot": 76414411,
      "slotInEpoch": 209611,
      "at": "2022-11-09T08:58:22+01:00"
    },
    {
      "no": 17,
      "slot": 76450051,
      "slotInEpoch": 245251,
      "at": "2022-11-09T18:52:22+01:00"
    },
    {
      "no": 18,
      "slot": 76454079,
      "slotInEpoch": 249279,
      "at": "2022-11-09T19:59:30+01:00"
    },
    {
      "no": 19,
      "slot": 76458071,
      "slotInEpoch": 253271,
      "at": "2022-11-09T21:06:02+01:00"
    },
    {
      "no": 20,
      "slot": 76470747,
      "slotInEpoch": 265947,
      "at": "2022-11-10T00:37:18+01:00"
    },
    {
      "no": 21,
      "slot": 76485320,
      "slotInEpoch": 280520,
      "at": "2022-11-10T04:40:11+01:00"
    },
    {
      "no": 22,
      "slot": 76500542,
      "slotInEpoch": 295742,
      "at": "2022-11-10T08:53:53+01:00"
    },
    {
      "no": 23,
      "slot": 76501157,
      "slotInEpoch": 296357,
      "at": "2022-11-10T09:04:08+01:00"
    },
    {
      "no": 24,
      "slot": 76559836,
      "slotInEpoch": 355036,
      "at": "2022-11-11T01:22:07+01:00"
    },
    {
      "no": 25,
      "slot": 76604336,
      "slotInEpoch": 399536,
      "at": "2022-11-11T13:43:47+01:00"
    },
    {
      "no": 26,
      "slot": 76618584,
      "slotInEpoch": 413784,
      "at": "2022-11-11T17:41:15+01:00"
    },
    {
      "no": 27,
      "slot": 76625638,
      "slotInEpoch": 420838,
      "at": "2022-11-11T19:38:49+01:00"
    },
    {
      "no": 28,
      "slot": 76634370,
      "slotInEpoch": 429570,
      "at": "2022-11-11T22:04:21+01:00"
    }
  ]
}
