{
  "status": "ok",
  "epoch": 394,
  "epochNonce": "46a37dc80a9fde65c333b863810dc88cc85e3d059cce665bd59c2963197d6c3e",
  "consensus": "praos",
  "epochSlots": 27,
  "epochSlotsIdeal": 19.44,
  "maxPerformance": 138.89,
  "poolId": "6c518b4861bb88b1395ceb116342cecbcfb8736282655f9a61c4c368",
  "sigma": 0.0009002246612287012,
  "activeStake": 22945427962960,
  "totalActiveStake": 25488557413704016,
  "d": 0,
  "f": 0.05,
  "assignedSlots": [
    {
      "no": 1,
      "slot": 84851287,
      "slotInEpoch": 6487,
      "at": "2023-02-15T00:32:58+01:00"
    },
    {
      "no": 2,
      "slot": 84863281,
      "slotInEpoch": 18481,
      "at": "2023-02-15T03:52:52+01:00"
    },
    {
      "no": 3,
      "slot": 84871171,
      "slotInEpoch": 26371,
      "at": "2023-02-15T06:04:22+01:00"
    },
    {
      "no": 4,
      "slot": 84898358,
      "slotInEpoch": 53558,
      "at": "2023-02-15T13:37:29+01:00"
    },
    {
      "no": 5,
      "slot": 84963949,
      "slotInEpoch": 119149,
      "at": "2023-02-16T07:50:40+01:00"
    },
    {
      "no": 6,
      "slot": 84968803,
      "slotInEpoch": 124003,
      "at": "2023-02-16T09:11:34+01:00"
    },
    {
      "no": 7,
      "slot": 84978722,
      "slotInEpoch": 133922,
      "at": "2023-02-16T11:56:53+01:00"
    },
    {
      "no": 8,
      "slot": 84994846,
      "slotInEpoch": 150046,
      "at": "2023-02-16T16:25:37+01:00"
    },
    {
      "no": 9,
      "slot": 85008159,
      "slotInEpoch": 163359,
      "at": "2023-02-16T20:07:30+01:00"
    },
    {
      "no": 10,
      "slot": 85074111,
      "slotInEpoch": 229311,
      "at": "2023-02-17T14:26:42+01:00"
    },
    {
      "no": 11,
      "slot": 85081185,
      "slotInEpoch": 236385,
      "at": "2023-02-17T16:24:36+01:00"
    },
    {
      "no": 12,
      "slot": 85087336,
      "slotInEpoch": 242536,
      "at": "2023-02-17T18:07:07+01:00"
    },
    {
      "no": 13,
      "slot": 85099007,
      "slotInEpoch": 254207,
      "at": "2023-02-17T21:21:38+01:00"
    },
    {
      "no": 14,
      "slot": 85110576,
      "slotInEpoch": 265776,
      "at": "2023-02-18T00:34:27+01:00"
    },
    {
      "no": 15,
      "slot": 85123512,
      "slotInEpoch": 278712,
      "at": "2023-02-18T04:10:03+01:00"
    },
    {
      "no": 16,
      "slot": 85124084,
      "slotInEpoch": 279284,
      "at": "2023-02-18T04:19:35+01:00"
    },
    {
      "no": 17,
      "slot": 85147307,
      "slotInEpoch": 302507,
      "at": "2023-02-18T10:46:38+01:00"
    },
    {
      "no": 18,
      "slot": 85151830,
      "slotInEpoch": 307030,
      "at": "2023-02-18T12:02:01+01:00"
    },
    {
      "no": 19,
      "slot": 85172261,
      "slotInEpoch": 327461,
      "at": "2023-02-18T17:42:32+01:00"
    },
    {
      "no": 20,
      "slot": 85188283,
      "slotInEpoch": 343483,
      "at": "2023-02-18T22:09:34+01:00"
    },
    {
      "no": 21,
      "slot": 85189904,
      "slotInEpoch": 345104,
      "at": "2023-02-18T22:36:35+01:00"
    },
    {
      "no": 22,
      "slot": 85193975,
      "slotInEpoch": 349175,
      "at": "2023-02-18T23:44:26+01:00"
    },
    {
      "no": 23,
      "slot": 85196503,
      "slotInEpoch": 351703,
      "at": "2023-02-19T00:26:34+01:00"
    },
    {
      "no": 24,
      "slot": 85207466,
      "slotInEpoch": 362666,
      "at": "2023-02-19T03:29:17+01:00"
    },
    {
      "no": 25,
      "slot": 85224323,
      "slotInEpoch": 379523,
      "at": "2023-02-19T08:10:14+01:00"
    },
    {
      "no": 26,
      "slot": 85236132,
      "slotInEpoch": 391332,
      "at": "2023-02-19T11:27:03+01:00"
    },
    {
      "no": 27,
      "slot": 85257066,
      "slotInEpoch": 412266,
      "at": "2023-02-19T17:15:57+01:00"
    }
  ]
}
